common/__init__.py
common/autogui.py
common/case_data_process.py
common/generate_test_code.py
common/guitools.py
common/main.py
medcase/__init__.py
medcase/autogui.py
medcase/case_data_process.py
medcase/generate_test_code.py
medcase/guitools.py
medcase/main.py
testdata/__init__.py
testdata/case_template.py
medcase-0.1.8.dist-info/METADATA
medcase-0.1.8.dist-info/WHEEL
medcase-0.1.8.dist-info/entry_points.txt
medcase-0.1.8.dist-info/top_level.txt
medcase-0.1.8.dist-info/RECORD
