Metadata-Version: 2.1
Name: medcase
Version: 0.1.8
Summary: UNKNOWN
Home-page: UNKNOWN
Author: UNKNOWN
Author-email: UNKNOWN
License: UNKNOWN
Platform: UNKNOWN
Requires-Dist: datetime
Requires-Dist: requests
Requires-Dist: tkcalendar
